watchmen_data_surface/__init__.py
watchmen_data_surface/cache/__init__.py
watchmen_data_surface/cache/cache_router.py
watchmen_data_surface/data/__init__.py
watchmen_data_surface/data/topic_data_router.py
watchmen_data_surface/main.py
watchmen_data_surface/settings.py
watchmen_data_surface-18.0.1.dist-info/METADATA
watchmen_data_surface-18.0.1.dist-info/WHEEL
watchmen_data_surface-18.0.1.dist-info/licenses/LICENSE
watchmen_data_surface-18.0.1.dist-info/RECORD
