Metadata-Version: 2.4
Name: watchmen-data-surface
Version: 18.0.1
Summary: 
License: MIT
License-File: LICENSE
Author: botlikes
Author-email: 75356972+botlikes456@users.noreply.github.com
Requires-Python: >=3.12,<3.13
Classifier: License :: OSI Approved :: MIT License
Classifier: Programming Language :: Python :: 3
Classifier: Programming Language :: Python :: 3.12
Provides-Extra: mongodb
Provides-Extra: mssql
Provides-Extra: mysql
Provides-Extra: oracle
Provides-Extra: oss
Provides-Extra: postgresql
Provides-Extra: s3
Requires-Dist: watchmen-data-kernel (==18.0.1)
Requires-Dist: watchmen-rest (==18.0.1)
Requires-Dist: watchmen-storage-mongodb (==18.0.1) ; extra == "mongodb"
Requires-Dist: watchmen-storage-mssql (==18.0.1) ; extra == "mssql"
Requires-Dist: watchmen-storage-mysql (==18.0.1) ; extra == "mysql"
Requires-Dist: watchmen-storage-oracle (==18.0.1) ; extra == "oracle"
Requires-Dist: watchmen-storage-oss (==18.0.1) ; extra == "oss"
Requires-Dist: watchmen-storage-postgresql (==18.0.1) ; extra == "postgresql"
Requires-Dist: watchmen-storage-s3 (==18.0.1) ; extra == "s3"
